README.md
setup.cfg
setup.py
pypeerassets/__init__.py
pypeerassets/__main__.py
pypeerassets/card_parsers.py
pypeerassets/exceptions.py
pypeerassets/kutil.py
pypeerassets/networks.py
pypeerassets/pa_constants.py
pypeerassets/paproto_pb2.py
pypeerassets/pautils.py
pypeerassets/pavoteproto_pb2.py
pypeerassets/protocol.py
pypeerassets/transactions.py
pypeerassets/voting.py
pypeerassets.egg-info/PKG-INFO
pypeerassets.egg-info/SOURCES.txt
pypeerassets.egg-info/dependency_links.txt
pypeerassets.egg-info/requires.txt
pypeerassets.egg-info/top_level.txt
pypeerassets/provider/__init__.py
pypeerassets/provider/common.py
pypeerassets/provider/cryptoid.py
pypeerassets/provider/electrum-server.py
pypeerassets/provider/explorer.py
pypeerassets/provider/rpcnode.py
test/test_kutil.py
test/test_networks.py
test/test_pa_constants.py
test/test_pautils.py
test/test_peerassets.py
test/test_protocol.py
test/test_provider.py
test/test_provider_cryptoid.py
test/test_provider_explorer.py
test/test_transactions.py