Metadata-Version: 1.0
Name: pypeerassets
Version: 0.4.8
Summary: Python implementation of the PeerAssets protocol.
Home-page: https://github.com/peerassets/pypeerassets
Author: PeerAssets
Author-email: peerchemist@protonmail.ch
License: BSD
Keywords: blockchain,digital assets,protocol
Platform: UNKNOWN
